say_hello898989/__init__.py
say_hello898989/say_hello_yapbarry.py
Sayhelloyapbarry2-1.0.dist-info/METADATA
Sayhelloyapbarry2-1.0.dist-info/WHEEL
Sayhelloyapbarry2-1.0.dist-info/top_level.txt
Sayhelloyapbarry2-1.0.dist-info/RECORD
