Metadata-Version: 2.1
Name: Sayhelloyapbarry2
Version: 1.0
Summary: custom function to help perform proprocessing functions like standard scaling etc
Author: Barry Yap
Author-email: yapweiminbarry@gmail.com
